pyaikit/__init__.py
pyaikit/authentication.py
pyaikit/example.py
pyaikit/setup.py
pyaikit/sentiment_analysis/sentiment_analyzer.py
pyaikit/text_generation/text_generator.py
pyaikit/text_summerization/text_summerizer.py
pyaikit/translation/translator.py
pyaikit-1.0.4.dist-info/METADATA
pyaikit-1.0.4.dist-info/WHEEL
pyaikit-1.0.4.dist-info/top_level.txt
pyaikit-1.0.4.dist-info/RECORD
