Metadata-Version: 2.1
Name: pyaikit
Version: 1.0.4
Summary: PyAIKit is a user-friendly Python package that simplifies the integration and usage of OpenAIs powerful ChatGPT API for natural language processing tasks
Home-page: https://github.com/somenath24/pyaikit
Author: Somenath Sit
Author-email: somenath.bhu.2010@gmail.com
Project-URL: GitHub, https://github.com/somenath24/pyaikit
Project-URL: Changelog, https://github.com/Somenath24/pyaikit/blob/main/CHANGELOG.md
Classifier: License :: OSI Approved :: MIT License
Classifier: Intended Audience :: Developers
Classifier: Programming Language :: Python :: 3
Classifier: Programming Language :: Python :: 3.9
Requires-Python: >=3.6
Requires-Dist: openai
Requires-Dist: pandas
Requires-Dist: requests
Requires-Dist: PyPDF2
Requires-Dist: PySimpleGUI
